odoo10_addon_account_bank_statement_import_save_file-10.0.1.0.0-py2.7-nspkg.pth
odoo10_addon_account_bank_statement_import_save_file-10.0.1.0.0.dist-info/top_level.txt
odoo10_addon_account_bank_statement_import_save_file-10.0.1.0.0.dist-info/WHEEL
odoo10_addon_account_bank_statement_import_save_file-10.0.1.0.0.dist-info/RECORD
odoo10_addon_account_bank_statement_import_save_file-10.0.1.0.0.dist-info/metadata.json
odoo10_addon_account_bank_statement_import_save_file-10.0.1.0.0.dist-info/DESCRIPTION.rst
odoo10_addon_account_bank_statement_import_save_file-10.0.1.0.0.dist-info/METADATA
odoo10_addon_account_bank_statement_import_save_file-10.0.1.0.0.dist-info/namespace_packages.txt
odoo/addons/account_bank_statement_import_save_file/__manifest__.py
odoo/addons/account_bank_statement_import_save_file/hooks.py
odoo/addons/account_bank_statement_import_save_file/__init__.py
odoo/addons/account_bank_statement_import_save_file/README.rst
odoo/addons/account_bank_statement_import_save_file/models/account_bank_statement_import.py
odoo/addons/account_bank_statement_import_save_file/models/account_bank_statement.py
odoo/addons/account_bank_statement_import_save_file/models/__init__.py
odoo/addons/account_bank_statement_import_save_file/i18n/it.po
odoo/addons/account_bank_statement_import_save_file/i18n/es.po
odoo/addons/account_bank_statement_import_save_file/i18n/lt.po
odoo/addons/account_bank_statement_import_save_file/i18n/lt_LT.po
odoo/addons/account_bank_statement_import_save_file/i18n/sl.po
odoo/addons/account_bank_statement_import_save_file/i18n/pt_PT.po
odoo/addons/account_bank_statement_import_save_file/i18n/nl.po
odoo/addons/account_bank_statement_import_save_file/i18n/de.po
odoo/addons/account_bank_statement_import_save_file/i18n/fr.po
odoo/addons/account_bank_statement_import_save_file/i18n/pt_BR.po
odoo/addons/account_bank_statement_import_save_file/i18n/fi.po
odoo/addons/account_bank_statement_import_save_file/views/account_bank_statement.xml
odoo/addons/account_bank_statement_import_save_file/tests/test_save_file.py
odoo/addons/account_bank_statement_import_save_file/tests/__init__.py
odoo/addons/account_bank_statement_import_save_file/static/description/icon.png
