Metadata-Version: 2.0
Name: odoo10-addon-account-bank-statement-import-save-file
Version: 10.0.1.0.0
Summary: Keep imported bank statements as raw data
Home-page: UNKNOWN
Author: Odoo Community Association (OCA), Therp BV
Author-email: support@odoo-community.org
License: AGPL-3
Platform: UNKNOWN
Requires-Dist: odoo (<10.1dev,>=10.0)
Classifier: Programming Language :: Python :: 2.7
Classifier: Framework :: Odoo
Classifier: License :: OSI Approved :: GNU Affero General Public License v3
